c_module.abi3.so
hello_lib.abi3.h
hello_lib.abi3.so
red.abi3.h
red.abi3.so
sum_go.abi3.h
sum_go.abi3.so
sum_pure_go.abi3.h
sum_pure_go.abi3.so
setuptools_golang_examples-2.2.0.dist-info/LICENSE
setuptools_golang_examples-2.2.0.dist-info/METADATA
setuptools_golang_examples-2.2.0.dist-info/WHEEL
setuptools_golang_examples-2.2.0.dist-info/top_level.txt
setuptools_golang_examples-2.2.0.dist-info/RECORD
